test_zjh_mcp_demo/__init__.py
test_zjh_mcp_demo-0.1.0.dist-info/METADATA
test_zjh_mcp_demo-0.1.0.dist-info/WHEEL
test_zjh_mcp_demo-0.1.0.dist-info/entry_points.txt
test_zjh_mcp_demo-0.1.0.dist-info/RECORD
