Metadata-Version: 2.4
Name: test-zjh-mcp-demo
Version: 0.1.0
Summary: Add your description here
Author-email: 3120005043_张俊鸿 <1017328759@qq.com>
Requires-Python: >=3.13
Requires-Dist: mcp[cli]>=1.10.1
